mdba_gauge_getter/__init__.py
mdba_gauge_getter/gauge_getter.py
mdba_gauge_getter/version.py
mdba_gauge_getter/data/bom_gauge_data.csv
mdba_gauge_getter-0.5.1.dist-info/LICENCE
mdba_gauge_getter-0.5.1.dist-info/METADATA
mdba_gauge_getter-0.5.1.dist-info/WHEEL
mdba_gauge_getter-0.5.1.dist-info/top_level.txt
mdba_gauge_getter-0.5.1.dist-info/RECORD
