Metadata-Version: 2.1
Name: mdba_gauge_getter
Version: 0.5.1
Summary: Facilitates waterflow gauge data ingest from several endpoints. Dependency to several other projects.
Home-page: https://github.com/MDBAuth/MDBA_Gauge_Getter
Author: Murray Darling Basin Authority
Author-email: ben.bradshaw@mdba.gov.au
Project-URL: Bug Tracker, https://github.com/MDBAuth/MDBA_Gauge_Getter/issues
Classifier: Operating System :: OS Independent
Classifier: Programming Language :: Python :: 3.7
Classifier: Programming Language :: Python :: 3.8
Classifier: Programming Language :: Python :: 3.9
Classifier: Programming Language :: Python :: 3.10
Classifier: Programming Language :: Python :: 3.11
Classifier: Framework :: Pytest
Requires-Python: >=3.7
License-File: LICENCE
Requires-Dist: pandas
Requires-Dist: requests
Requires-Dist: bomwater
